meglio/__init__.py
meglio/analysis/__init__.py
meglio/analysis/statistical_diff.py
meglio/model/__init__.py
meglio/model/cpu_sched_slice.py
meglio/model/slice.py
meglio/model/slice_set.py
meglio/util/__init__.py
meglio/util/trace_processor.py
meglio-0.0.7.dist-info/LICENSE.md
meglio-0.0.7.dist-info/METADATA
meglio-0.0.7.dist-info/WHEEL
meglio-0.0.7.dist-info/top_level.txt
meglio-0.0.7.dist-info/RECORD
