Metadata-Version: 2.1
Name: meglio
Version: 0.0.7
Author: Jason C.H
Author-email: ctrysbita@outlook.com
License-File: LICENSE.md
Requires-Dist: perfetto
